[
    {
        "id": 7,
        "email": "michael.lawson@fusemachines.com",
        "first_name": "Michael",
        "last_name": "Lawson",
        "avatar": "https://reqres.in/img/faces/7-image.jpg"
    },
    {
        "id": 9,
        "email": "tobias.funke@reqres.in",
        "first_name": "Tobias",
        "last_name": "Funke",
        "avatar": "https://reqres.in/img/faces/9-image.jpg"
    },
    {
        "id": 10,
        "email": "byron.fields@reqres.in",
        "first_name": "Byron",
        "last_name": "Fields",
        "avatar": "https://reqres.in/img/faces/10-image.jpg"
    },
    {
        "id": 11,
        "email": "george.edwards@reqres.in",
        "first_name": "George",
        "last_name": "Edwards",
        "avatar": "https://reqres.in/img/faces/11-image.jpg"
    },
    {
        "id": 12,
        "email": "rachel.howell@reqres.in",
        "first_name": "Rachel",
        "last_name": "Howell",
        "avatar": "https://reqres.in/img/faces/12-image.jpg"
    },
    {
        "id": 13,
        "email": "sanaya.ghimire@reqres.in",
        "first_name": "sanaya",
        "last_name": "ghimire",
        "avatar": "https://reqres.in/img/faces/9-image.jpg"
    },
    {
        "id": 14,

        
        "email": "sanaya.ghimire@reqres.in",
        "first_name": "sanaya",
        "last_name": "ghimire",
        "avatar": "https://reqres.in/img/faces/9-image.jpg"
    }
]